pntl/__init__.py
pntl/cli.py
pntl/depParse.sh
pntl/lexparser.sh
pntl/stanford-parser.jar
pntl/tools.py
pntl/utils.py
pntl-0.2.4.dist-info/DESCRIPTION.rst
pntl-0.2.4.dist-info/METADATA
pntl-0.2.4.dist-info/RECORD
pntl-0.2.4.dist-info/WHEEL
pntl-0.2.4.dist-info/entry_points.txt
pntl-0.2.4.dist-info/metadata.json
pntl-0.2.4.dist-info/top_level.txt
