Metadata-Version: 2.0
Name: pntl
Version: 0.2.4
Summary: used to interface with Senna and stanford-parser.jar for dependency parsing
Home-page: https://github.com/jawahar273/practNLPTools-lite
Author: Jawahar S
Author-email: jawahar273@gmail.com
License: MIT license
Keywords: practnlptools-lite,senna,python,pntl,pysenna
Platform: UNKNOWN
Classifier: Development Status :: 4 - Beta
Classifier: Intended Audience :: Developers
Classifier: License :: OSI Approved :: MIT License
Classifier: Natural Language :: English
Classifier: Programming Language :: Python :: 3.3
Classifier: Programming Language :: Python :: 3.4
Classifier: Programming Language :: Python :: 3.5
Classifier: Programming Language :: Python :: 3.6
Classifier: Topic :: Scientific/Engineering :: Information Analysis
Requires-Dist: Click (>=6.0)
Requires-Dist: colorama (>=0.3.9)
